pdflib_extended/__init__.py
pdflib_extended/core/__init__.py
pdflib_extended/core/binaries/pdflib/_10/linux/pdflib_py.pyi
pdflib_extended/core/binaries/pdflib/_10/linux/pdflib_py.so
pdflib_extended/core/binaries/pdflib/_10/windows/pdflib_py.pyd
pdflib_extended/core/binaries/pdflib/_10/windows/pdflib_py.pyi
pdflib_extended/core/binaries/pdflib/_931/linux/pdflib_py.pyi
pdflib_extended/core/binaries/pdflib/_931/linux/pdflib_py.so
pdflib_extended/core/binaries/pdflib/_931/windows/pdflib_py.pyd
pdflib_extended/core/binaries/pdflib/_931/windows/pdflib_py.pyi
pdflib_extended/core/binaries/tetlib/_55/linux/tetlib_py.pyi
pdflib_extended/core/binaries/tetlib/_55/linux/tetlib_py.so
pdflib_extended/core/binaries/tetlib/_55/windows/tetlib_py.pyd
pdflib_extended/core/binaries/tetlib/_55/windows/tetlib_py.pyi
pdflib_extended/core/pdflib_base.py
pdflib_extended/core/tetlib_base.py
pdflib_extended/exceptions.py
pdflib_extended/extensions/__init__.py
pdflib_extended/extensions/barcodes.py
pdflib_extended/extensions/blocks.py
pdflib_extended/extensions/classes.py
pdflib_extended/extensions/contexts.py
pdflib_extended/extensions/shapes.py
pdflib_extended/extensions/text.py
pdflib_extended/pdflib.py
pdflib_extended/py.typed
pdflib_extended/resources/fonts/LibreBarcode128-Regular.ttf
pdflib_extended/resources/fonts/OpenSans-Regular.ttf
pdflib_extended/resources/fonts/USPSIMBCompact.ttf
pdflib_extended/resources/fonts/USPSIMBStandard.ttf
pdflib_extended/tetlib.py
pdflib_extended-2025.9.16.dist-info/METADATA
pdflib_extended-2025.9.16.dist-info/WHEEL
pdflib_extended-2025.9.16.dist-info/RECORD
