Metadata-Version: 2.1
Name: pdflib-extended
Version: 2025.9.16
Summary: Extension of the PDFlib library.
Author: RichardS
Author-email: richards@eoshost.com
Requires-Python: >=3.9,<4.0
Classifier: Programming Language :: Python :: 3
Classifier: Programming Language :: Python :: 3.9
Classifier: Programming Language :: Python :: 3.10
Classifier: Programming Language :: Python :: 3.11
Classifier: Programming Language :: Python :: 3.12
Classifier: Programming Language :: Python :: 3.13
Requires-Dist: pillow (>=10.3.0,<11.0.0)
Requires-Dist: pylibdmtx (>=0.1.10,<0.2.0)
Requires-Dist: pywin32 ; sys_platform == "win32"
Requires-Dist: qrcode (>=8.0,<9.0)
